LICENSE
MANIFEST.in
README.rst
setup.py
django_socketio/__init__.py
django_socketio/channels.py
django_socketio/clients.py
django_socketio/events.py
django_socketio/models.py
django_socketio/settings.py
django_socketio/tests.py
django_socketio/urls.py
django_socketio/utils.py
django_socketio/views.py
django_socketio.egg-info/PKG-INFO
django_socketio.egg-info/SOURCES.txt
django_socketio.egg-info/dependency_links.txt
django_socketio.egg-info/not-zip-safe
django_socketio.egg-info/requires.txt
django_socketio.egg-info/top_level.txt
django_socketio/example_project/__init__.py
django_socketio/example_project/dev.db
django_socketio/example_project/manage.py
django_socketio/example_project/settings.py
django_socketio/example_project/urls.py
django_socketio/example_project/chat/__init__.py
django_socketio/example_project/chat/events.py
django_socketio/example_project/chat/models.py
django_socketio/example_project/chat/urls.py
django_socketio/example_project/chat/views.py
django_socketio/example_project/chat/static/css/chat.css
django_socketio/example_project/chat/static/js/chat.js
django_socketio/example_project/chat/templates/base.html
django_socketio/example_project/chat/templates/room.html
django_socketio/example_project/chat/templates/rooms.html
django_socketio/example_project/chat/templates/system_message.html
django_socketio/management/__init__.py
django_socketio/management/commands/__init__.py
django_socketio/management/commands/runserver_socketio.py
django_socketio/static/js/socket.io.js
django_socketio/templates/socketio_scripts.html
django_socketio/templatetags/__init__.py
django_socketio/templatetags/socketio_tags.py