Metadata-Version: 1.0
Name: django-socketio
Version: 0.3.7
Summary: A Django app providing the features required to use websockets with Django via Socket.IO
Home-page: http://github.com/stephenmcd/django-socketio
Author: Stephen McDonald
Author-email: steve@jupo.org
License: UNKNOWN
Platform: UNKNOWN
Classifier: Development Status :: 4 - Beta
Classifier: Environment :: Web Environment
Classifier: Framework :: Django
Classifier: Intended Audience :: Developers
Classifier: License :: OSI Approved :: BSD License
Classifier: Operating System :: POSIX
Classifier: Programming Language :: Python
Classifier: Topic :: Internet :: WWW/HTTP
Classifier: Topic :: Internet :: WWW/HTTP :: HTTP Servers
Classifier: Topic :: Internet :: WWW/HTTP :: WSGI
